Workbook

Sheet 🏠 Proyectos
A1: PORTAFOLIO DE PROYECTOS INMOBILIARIOS
A2: ID | B2: Nombre Proyecto | C2: Tipo | D2: Ciudad | E2: Barrio/Sector | F2: Total Unidades | G2: Vendidas | H2: Reservadas | I2: Disponibles | J2: Precio m² (COP) | K2: Estado
A3: PRY-001 | B3: Torres del Poblado | C3: Apartamentos | D3: Medellín | E3: El Poblado | F3: 120 | G3: =COUNTIFS('📋 Pipeline Comercial'!$C$3:$C,A3,'📋 Pipeline Comercial'!$F$3:$F,"Ganado") | H3: =COUNTIFS('📋 Pipeline Comercial'!$C$3:$C,A3,'📋 Pipeline Comercial'!$F$3:$F,"Negociación")+COUNTIFS('📋 Pipeline Comercial'!$C$3:$C,A3,'📋 Pipeline Comercial'!$F$3:$F,"Cierre") | I3: =F3-G3-H3 | J3: 9500000 | K3: =IF(I3<=0,"Agotado",IF(G3/F3>=0.9,"Casi agotado","En venta"))
A4: PRY-002 | B4: Reserva Santa Elena | C4: Casas | D4: Medellín | E4: Santa Elena | F4: 60 | G4: =COUNTIFS('📋 Pipeline Comercial'!$C$3:$C,A4,'📋 Pipeline Comercial'!$F$3:$F,"Ganado") | H4: =COUNTIFS('📋 Pipeline Comercial'!$C$3:$C,A4,'📋 Pipeline Comercial'!$F$3:$F,"Negociación")+COUNTIFS('📋 Pipeline Comercial'!$C$3:$C,A4,'📋 Pipeline Comercial'!$F$3:$F,"Cierre") | I4: =F4-G4-H4 | J4: 6800000 | K4: =IF(I4<=0,"Agotado",IF(G4/F4>=0.9,"Casi agotado","En venta"))
A5: PRY-003 | B5: Conecta Laureles | C5: Aptos. Estudio | D5: Medellín | E5: Laureles | F5: 200 | G5: =COUNTIFS('📋 Pipeline Comercial'!$C$3:$C,A5,'📋 Pipeline Comercial'!$F$3:$F,"Ganado") | H5: =COUNTIFS('📋 Pipeline Comercial'!$C$3:$C,A5,'📋 Pipeline Comercial'!$F$3:$F,"Negociación")+COUNTIFS('📋 Pipeline Comercial'!$C$3:$C,A5,'📋 Pipeline Comercial'!$F$3:$F,"Cierre") | I5: =F5-G5-H5 | J5: 7200000 | K5: =IF(I5<=0,"Agotado",IF(G5/F5>=0.9,"Casi agotado","En venta"))
A6: PRY-004 | B6: Altavista Park | C6: Casas | D6: Medellín | E6: Altavista | F6: 80 | G6: =COUNTIFS('📋 Pipeline Comercial'!$C$3:$C,A6,'📋 Pipeline Comercial'!$F$3:$F,"Ganado") | H6: =COUNTIFS('📋 Pipeline Comercial'!$C$3:$C,A6,'📋 Pipeline Comercial'!$F$3:$F,"Negociación")+COUNTIFS('📋 Pipeline Comercial'!$C$3:$C,A6,'📋 Pipeline Comercial'!$F$3:$F,"Cierre") | I6: =F6-G6-H6 | J6: 5900000 | K6: =IF(I6<=0,"Agotado",IF(G6/F6>=0.9,"Casi agotado","En venta"))
A7: PRY-005 | B7: Ciudadela Rionegro | C7: Aptos. / Casas | D7: Rionegro | E7: Centro | F7: 150 | G7: =COUNTIFS('📋 Pipeline Comercial'!$C$3:$C,A7,'📋 Pipeline Comercial'!$F$3:$F,"Ganado") | H7: =COUNTIFS('📋 Pipeline Comercial'!$C$3:$C,A7,'📋 Pipeline Comercial'!$F$3:$F,"Negociación")+COUNTIFS('📋 Pipeline Comercial'!$C$3:$C,A7,'📋 Pipeline Comercial'!$F$3:$F,"Cierre") | I7: =F7-G7-H7 | J7: 4800000 | K7: =IF(I7<=0,"Agotado",IF(G7/F7>=0.9,"Casi agotado","En venta"))
A8: PRY-006 | B8: Plaza Bello | C8: Locales Comercial | D8: Bello | E8: Centro | F8: 40 | G8: =COUNTIFS('📋 Pipeline Comercial'!$C$3:$C,A8,'📋 Pipeline Comercial'!$F$3:$F,"Ganado") | H8: =COUNTIFS('📋 Pipeline Comercial'!$C$3:$C,A8,'📋 Pipeline Comercial'!$F$3:$F,"Negociación")+COUNTIFS('📋 Pipeline Comercial'!$C$3:$C,A8,'📋 Pipeline Comercial'!$F$3:$F,"Cierre") | I8: =F8-G8-H8 | J8: 8100000 | K8: =IF(I8<=0,"Agotado",IF(G8/F8>=0.9,"Casi agotado","En venta"))
A9: PRY-007 | B9: Mirador de Envigado | C9: Apartamentos | D9: Envigado | E9: Loma del Escobero | F9: 90 | G9: =COUNTIFS('📋 Pipeline Comercial'!$C$3:$C,A9,'📋 Pipeline Comercial'!$F$3:$F,"Ganado") | H9: =COUNTIFS('📋 Pipeline Comercial'!$C$3:$C,A9,'📋 Pipeline Comercial'!$F$3:$F,"Negociación")+COUNTIFS('📋 Pipeline Comercial'!$C$3:$C,A9,'📋 Pipeline Comercial'!$F$3:$F,"Cierre") | I9: =F9-G9-H9 | J9: 8700000 | K9: =IF(I9<=0,"Agotado",IF(G9/F9>=0.9,"Casi agotado","En venta"))
A10: PRY-008 | B10: Valle Verde Itagüí | C10: Casas VIS | D10: Itagüí | E10: Santa María | F10: 110 | G10: =COUNTIFS('📋 Pipeline Comercial'!$C$3:$C,A10,'📋 Pipeline Comercial'!$F$3:$F,"Ganado") | H10: =COUNTIFS('📋 Pipeline Comercial'!$C$3:$C,A10,'📋 Pipeline Comercial'!$F$3:$F,"Negociación")+COUNTIFS('📋 Pipeline Comercial'!$C$3:$C,A10,'📋 Pipeline Comercial'!$F$3:$F,"Cierre") | I10: =F10-G10-H10 | J10: 3200000 | K10: =IF(I10<=0,"Agotado",IF(G10/F10>=0.9,"Casi agotado","En venta"))

Sheet 👥 Clientes
A1: BASE DE CLIENTES / LEADS CRM
A2: ID Cliente | B2: Nombre Completo | C2: Teléfono | D2: Email | E2: Ciudad | F2: Proyecto Interés | G2: Fuente | H2: Asesor | I2: Estado Lead | J2: Fecha Primer Contacto | K2: Fecha Seguimiento | L2: Observaciones
A3: CLI-0001 | B3: Cristian Muñoz Gómez | C3: 3244381905 | D3: cristian.munoz30@outlook.com | E3: Envigado | F3: PRY-001 | G3: Facebook | H3: Paula Arenas | I3: Ganado | J3: 45292 | K3: 45357 | L3: Compró Apto 1102 en Torres del Poblado
A4: CLI-0002 | B4: Daniela López Quintero | C4: 3018944621 | D4: daniela.lopez55@outlook.com | E4: Rionegro | F4: PRY-001 | G4: Portal Web | H4: Andrés Torres | I4: Ganado | J4: 45292 | K4: 45357 | L4: Compró Apto 303 en Torres del Poblado
A5: CLI-0003 | B5: Valeria Montoya Montes | C5: 3229349197 | D5: valeria.montoya28@outlook.com | E5: Medellín | F5: PRY-001 | G5: Referido | H5: Juliana Vélez | I5: Ganado | J5: 45292 | K5: 45357 | L5: Compró Apto 1601 en Torres del Poblado
A6: CLI-0004 | B6: Isabel Cardona Quintero | C6: 3234385063 | D6: isabel.cardona22@yahoo.com | E6: Itagüí | F6: PRY-001 | G6: Llamada directa | H6: Luis Bedoya | I6: Ganado | J6: 45292 | K6: 45357 | L6: Compró Apto 201 en Torres del Poblado
A7: CLI-0005 | B7: Verónica Higuita Peláez | C7: 3238901493 | D7: veronica.higuita87@gmail.com | E7: Sabaneta | F7: PRY-001 | G7: Referido | H7: Sofía Prada | I7: Ganado | J7: 45292 | K7: 45372 | L7: Compró Apto 804 en Torres del Poblado
A8: CLI-0006 | B8: Isabel Vélez Palacio | C8: 3107179436 | D8: isabel.velez41@yahoo.com | E8: Medellín | F8: PRY-001 | G8: Portal Web | H8: Sofía Prada | I8: Ganado | J8: 45292 | K8: 45392 | L8: Compró Apto 1106 en Torres del Poblado
A9: CLI-0007 | B9: Camila Ochoa Pérez | C9: 3011743562 | D9: camila.ochoa43@hotmail.com | E9: Medellín | F9: PRY-001 | G9: Referido | H9: Juliana Vélez | I9: Ganado | J9: 45292 | K9: 45395 | L9: Compró Apto 1504 en Torres del Poblado
A10: CLI-0008 | B10: Ximena Salazar Pérez | C10: 3238687979 | D10: ximena.salazar20@yahoo.com | E10: Medellín | F10: PRY-001 | G10: Portal Web | H10: Juliana Vélez | I10: Ganado | J10: 45292 | K10: 45401 | L10: Compró Apto 1405 en Torres del Poblado
A11: CLI-0009 | B11: Alejandro Gómez Ochoa | C11: 3176130229 | D11: alejandro.gomez43@hotmail.com | E11: Sabaneta | F11: PRY-001 | G11: Referido | H11: Ana Quintero | I11: Ganado | J11: 45292 | K11: 45408 | L11: Compró Apto 601 en Torres del Poblado
A12: CLI-0010 | B12: Liliana Bedoya Echeverri | C12: 3005001773 | D12: liliana.bedoya94@hotmail.com | E12: Medellín | F12: PRY-001 | G12: Referido | H12: Luis Bedoya | I12: Perdido | J12: 45292 | K12: 45327 | L12: No volvió a responder
A13: CLI-0011 | B13: Isabel Echeverri Marín | C13: 3008515183 | D13: isabel.echeverri49@hotmail.com | E13: Medellín | F13: PRY-001 | G13: Portal Web | H13: Miguel Salazar | I13: Perdido | J13: 45292 | K13: 45406 | L13: Crédito no aprobado
A14: CLI-0012 | B14: Ricardo Espinosa Palacio | C14: 3146738206 | D14: ricardo.espinosa42@hotmail.com | E14: Itagüí | F14: PRY-002 | G14: Feria Inmobiliaria | H14: Miguel Salazar | I14: Ganado | J14: 45292 | K14: 45388 | L14: Compró Casa 7 en Reserva Santa Elena
... A3057: CLI-3055 | B3057: Gloria López Rojas | C3057: 3145186432 | D3057: gloria.lopez94@gmail.com | E3057: Medellín | F3057: PRY-001 | G3057: Llamada directa | H3057: Juliana Vélez | I3057: Nuevo lead | J3057: 46203 | K3057: 46212 | L3057: Pendiente de primera llamada

Sheet 📋 Pipeline Comercial
A1: PIPELINE COMERCIAL — GESTIÓN DE VENTAS
A2: ID Negocio | B2: Cliente | C2: Proyecto | D2: Unidad | E2: Asesor | F2: Etapa | G2: Valor Venta (COP) | H2: % Probabilidad | I2: Fecha Apertura | J2: Fecha Cierre Est. | K2: Días en Etapa | L2: Observación
A3: NEG-0001 | B3: Cristian Muñoz Gómez | C3: PRY-001 | D3: Apto 1102 | E3: Paula Arenas | F3: Ganado | G3: 538000000 | H3: 1 | I3: 45292 | J3: 45327 | K3: 35 | L3: Promesa de compraventa firmada
A4: NEG-0002 | B4: Daniela López Quintero | C4: PRY-001 | D4: Apto 303 | E4: Andrés Torres | F4: Ganado | G4: 665000000 | H4: 1 | I4: 45292 | J4: 45327 | K4: 35 | L4: Promesa de compraventa firmada
A5: NEG-0003 | B5: Valeria Montoya Montes | C5: PRY-001 | D5: Apto 1601 | E5: Juliana Vélez | F5: Ganado | G5: 750000000 | H5: 1 | I5: 45292 | J5: 45327 | K5: 35 | L5: Promesa de compraventa firmada
A6: NEG-0004 | B6: Isabel Cardona Quintero | C6: PRY-001 | D6: Apto 201 | E6: Luis Bedoya | F6: Ganado | G6: 558000000 | H6: 1 | I6: 45292 | J6: 45327 | K6: 35 | L6: Promesa de compraventa firmada
A7: NEG-0005 | B7: Verónica Higuita Peláez | C7: PRY-001 | D7: Apto 804 | E7: Sofía Prada | F7: Ganado | G7: 570000000 | H7: 1 | I7: 45292 | J7: 45342 | K7: 50 | L7: Promesa de compraventa firmada
A8: NEG-0006 | B8: Isabel Vélez Palacio | C8: PRY-001 | D8: Apto 1106 | E8: Sofía Prada | F8: Ganado | G8: 584000000 | H8: 1 | I8: 45292 | J8: 45362 | K8: 70 | L8: Promesa de compraventa firmada
A9: NEG-0007 | B9: Camila Ochoa Pérez | C9: PRY-001 | D9: Apto 1504 | E9: Juliana Vélez | F9: Ganado | G9: 691000000 | H9: 1 | I9: 45292 | J9: 45365 | K9: 73 | L9: Promesa de compraventa firmada
A10: NEG-0008 | B10: Ximena Salazar Pérez | C10: PRY-001 | D10: Apto 1405 | E10: Juliana Vélez | F10: Ganado | G10: 721000000 | H10: 1 | I10: 45292 | J10: 45371 | K10: 79 | L10: Promesa de compraventa firmada
A11: NEG-0009 | B11: Alejandro Gómez Ochoa | C11: PRY-001 | D11: Apto 601 | E11: Ana Quintero | F11: Ganado | G11: 754000000 | H11: 1 | I11: 45292 | J11: 45378 | K11: 86 | L11: Promesa de compraventa firmada
A12: NEG-0010 | B12: Liliana Bedoya Echeverri | C12: PRY-001 | D12: Apto 2102 | E12: Luis Bedoya | F12: Perdido | G12: 747000000 | H12: 0 | I12: 45292 | J12: 45327 | K12: 35 | L12: No volvió a responder
A13: NEG-0011 | B13: Isabel Echeverri Marín | C13: PRY-001 | D13: Apto 502 | E13: Miguel Salazar | F13: Perdido | G13: 731000000 | H13: 0 | I13: 45292 | J13: 45406 | K13: 114 | L13: Crédito no aprobado
A14: NEG-0012 | B14: Ricardo Espinosa Palacio | C14: PRY-002 | D14: Casa 7 | E14: Miguel Salazar | F14: Ganado | G14: 695000000 | H14: 1 | I14: 45292 | J14: 45358 | K14: 66 | L14: Promesa de compraventa firmada
... A1062: NEG-1060 | B1062: Sandra Cardona Gaviria | C1062: PRY-007 | D1062: Apto 501 | E1062: Luis Bedoya | F1062: Prospección | G1062: 762000000 | H1062: 0.1 | I1062: 46199 | J1062: 46222 | K1062: 2 | L1062: Solicitó información por formulario

Sheet 💰 Financiero
A1: CONTROL FINANCIERO — INGRESOS Y CARTERA
A2: ID Pago | B2: Cliente | C2: Proyecto | D2: Concepto | E2: Valor Total (COP) | F2: Valor Pagado | G2: Valor Pendiente | H2: % Avance Pago | I2: Fecha Compromiso | J2: Estado Pago | K2: Asesor
A3: PAG-0001 | B3: Natalia Cardona Uribe | C3: PRY-008 | D3: Cuota inicial | E3: 33000000 | F3: 33000000 | G3: =E3-F3 | H3: =IF(E3>0,F3/E3,0) | I3: 46074 | J3: Pagado | K3: Miguel Salazar
A4: PAG-0002 | B4: Natalia Cardona Uribe | C4: PRY-008 | D4: Escrituración | E4: 132000000 | F4: 132000000 | G4: =E4-F4 | H4: =IF(E4>0,F4/E4,0) | I4: 46168 | J4: Pagado | K4: Miguel Salazar
A5: PAG-0003 | B5: Juliana Ríos López | C5: PRY-008 | D5: Cuota inicial | E5: 26000000 | F5: 26000000 | G5: =E5-F5 | H5: =IF(E5>0,F5/E5,0) | I5: 46074 | J5: Pagado | K5: Paula Arenas
A6: PAG-0004 | B6: Juliana Ríos López | C6: PRY-008 | D6: Escrituración | E6: 105000000 | F6: 105000000 | G6: =E6-F6 | H6: =IF(E6>0,F6/E6,0) | I6: 46130 | J6: Pagado | K6: Paula Arenas
A7: PAG-0005 | B7: Fernando Giraldo Mejía | C7: PRY-008 | D7: Cuota inicial | E7: 26000000 | F7: 26000000 | G7: =E7-F7 | H7: =IF(E7>0,F7/E7,0) | I7: 46074 | J7: Pagado | K7: Miguel Salazar
A8: PAG-0006 | B8: Fernando Giraldo Mejía | C8: PRY-008 | D8: Escrituración | E8: 102000000 | F8: 102000000 | G8: =E8-F8 | H8: =IF(E8>0,F8/E8,0) | I8: 46112 | J8: Pagado | K8: Miguel Salazar
A9: PAG-0007 | B9: Mateo Ríos Cifuentes | C9: PRY-003 | D9: Cuota inicial | E9: 95000000 | F9: 82500000 | G9: =E9-F9 | H9: =IF(E9>0,F9/E9,0) | I9: 46229 | J9: Al día | K9: Paula Arenas
A10: PAG-0008 | B10: Jhon Bedoya Echeverri | C10: PRY-003 | D10: Cuota inicial | E10: 116000000 | F10: 100411765 | G10: =E10-F10 | H10: =IF(E10>0,F10/E10,0) | I10: 46229 | J10: Al día | K10: Andrés Torres
A11: PAG-0009 | B11: Juliana Correa López | C11: PRY-003 | D11: Cuota inicial | E11: 106000000 | F11: 91882353 | G11: =E11-F11 | H11: =IF(E11>0,F11/E11,0) | I11: 46229 | J11: Al día | K11: Juliana Vélez
A12: PAG-0010 | B12: Hernán Duque Cardona | C12: PRY-003 | D12: Cuota inicial | E12: 102000000 | F12: 88470588 | G12: =E12-F12 | H12: =IF(E12>0,F12/E12,0) | I12: 46229 | J12: Al día | K12: Miguel Salazar
A13: PAG-0011 | B13: Rodrigo Echeverri Jaramillo | C13: PRY-003 | D13: Cuota inicial | E13: 110000000 | F13: 95294118 | G13: =E13-F13 | H13: =IF(E13>0,F13/E13,0) | I13: 46229 | J13: Al día | K13: Miguel Salazar
A14: PAG-0012 | B14: David Espinosa Giraldo | C14: PRY-003 | D14: Cuota inicial | E14: 90000000 | F14: 68181818 | G14: =E14-F14 | H14: =IF(E14>0,F14/E14,0) | I14: 46082 | J14: En mora | K14: Juliana Vélez
... A855: PAG-0853 | B855: Alejandro Salazar López | C855: PRY-006 | D855: Cuota inicial | E855: 155000000 | F855: 10000000 | G855: =E855-F855 | H855: =IF(E855>0,F855/E855,0) | I855: 46233 | J855: Al día | K855: Juliana Vélez
